pyvrt/__init__.py
pyvrt/http.py
pyvrt/traffic.py
pyvrt/weather.py
pyvrt/media/__init__.py
pyvrt/media/const.py
pyvrt/media/stubru.py
pyvrt-1.7.1.dist-info/LICENSE
pyvrt-1.7.1.dist-info/METADATA
pyvrt-1.7.1.dist-info/WHEEL
pyvrt-1.7.1.dist-info/top_level.txt
pyvrt-1.7.1.dist-info/RECORD
