Metadata-Version: 2.1
Name: pyvrt
Version: 1.7.1
Summary: Python library to interact with VRT public APIs
Home-page: https://github.com/thibmaek/pyvrt
Author: thibmaek
Author-email: thibault.maekelbergh@icloud.com
License: UNKNOWN
Platform: UNKNOWN
Classifier: Programming Language :: Python :: 3
Classifier: License :: OSI Approved :: MIT License
Classifier: Operating System :: OS Independent
Requires-Python: >=3.6
Requires-Dist: requests
